GiN/Galaxyuibuilder.py
GiN/__init__.py
GiN/_frontend.py
GiN/_version.py
GiN/authwidget.py
GiN/display.py
GiN/sessions.py
GiN/settings.py
GiN/shim.py
GiN/taskwidget.py
GiN/uioutput.py
GiN/util.py
GiN/labextension/package.json
GiN/labextension/static/177.65cbd751968fe186259d.js
GiN/labextension/static/397.26775095759b902c975f.js
GiN/labextension/static/43.9730d6fd17b18f9dd5dd.js
GiN/labextension/static/480.45971e753e7c1d2d2abf.js
GiN/labextension/static/568.87c0a54bc1cc90dc343a.js
GiN/labextension/static/669.f6c1a35a41f92250172b.js
GiN/labextension/static/755.f0419249c0d4a5f6c036.js
GiN/labextension/static/755.f0419249c0d4a5f6c036.js.LICENSE.txt
GiN/labextension/static/794.b78a08265faf48a05bf3.js
GiN/labextension/static/7f7e8263c4c886d64552d3e7dfc0304ed4a56a3636b7f68b95ba1c6be60d1f43.png
GiN/labextension/static/841.d43e8c8ca2b77e9b020e.js
GiN/labextension/static/remoteEntry.9a5582beebc2a8765769.js
GiN/labextension/static/style.js
GiN/labextension/static/third-party-licenses.json
GiN/nbextension/066dddb9220086e56a27a6c6986d0546.svg
GiN/nbextension/06de3f6f47040a96e1b75f57ff2be41f.svg
GiN/nbextension/084b59edab2415645e3e81e6a715dc08.svg
GiN/nbextension/09f3e4106c73962f016e29bf9aa511c6.svg
GiN/nbextension/0b22fba7dd1dd7b9b2f5cc46d4e2343c.svg
GiN/nbextension/0f1d43ae124df30d5d8ed5c5c99d3b5e.svg
GiN/nbextension/0fc6ae9cf3db8ad62b1ce50985ae4997.svg
GiN/nbextension/12d813858e2776ce290f56682563c552.svg
GiN/nbextension/130adcee3c98b618a4a668288c24587c.svg
GiN/nbextension/1423798505a006a4e17f17749ad544c8.svg
GiN/nbextension/173a84b6ef03e6433fb0895d08a46aeb.svg
GiN/nbextension/198b0cf0a6d5a82f0ff877fe941f534c.svg
GiN/nbextension/20879f46e732b69ab5942128421e7947.svg
GiN/nbextension/2384dc2d9b2863753727a0c5ce6f7150.svg
GiN/nbextension/24026a11d882b413caf54ea571fe1bd4.svg
GiN/nbextension/27799b9c71f8384579c91c8fe5fd1bf5.svg
GiN/nbextension/282072ef0b0d4c9e47b648afd96602a7.svg
GiN/nbextension/301d25ab1dc1903e2e511f116320d2c7.svg
GiN/nbextension/32d5545b19f6f168205599a61c2e9b57.svg
galaxylab-0.1.0a0.dist-info/METADATA
galaxylab-0.1.0a0.dist-info/WHEEL
galaxylab-0.1.0a0.dist-info/top_level.txt
galaxylab-0.1.0a0.dist-info/RECORD
